[
  {
    "groupName": "Cover Sheet",
    "questionIds": [
      "q1",
      "q2",
      "q3",
      "q4",
      "q5",
      "q6"
    ]
  },
  {
    "groupName": "IU",
    "questionIds": [
      "q16",
      "q17"
    ]
  },
  {
    "groupName": "xvsfv",
    "questionIds": [
      "q6"
    ]
  },
  {
    "groupName": "adasdasd",
    "questionIds": [
      "q12"
    ]
  },
  {
    "groupName": "IU",
    "questionIds": [
      "q37",
      "q38"
    ]
  },
  {
    "groupName": "adad",
    "questionIds": [
      "q26"
    ]
  },
  {
    "groupName": "Heading",
    "questionIds": [
      "q16",
      "q17",
      "q18",
      "q19",
      "q20",
      "q28",
      "q34",
      "q35"
    ]
  },
  {
    "groupName": "Hiding",
    "questionIds": [
      "q2",
      "q3",
      "q4"
    ]
  }
]